README.rst
setup.cfg
setup.py
autobahn_sync/__init__.py
autobahn_sync/api.py
autobahn_sync/callbacks_runner.py
autobahn_sync/core.py
autobahn_sync/exceptions.py
autobahn_sync/logger.py
autobahn_sync/session.py
autobahn_sync.egg-info/PKG-INFO
autobahn_sync.egg-info/SOURCES.txt
autobahn_sync.egg-info/dependency_links.txt
autobahn_sync.egg-info/not-zip-safe
autobahn_sync.egg-info/requires.txt
autobahn_sync.egg-info/top_level.txt
autobahn_sync/extensions/__init__.py
autobahn_sync/extensions/flask.py