Metadata-Version: 1.1
Name: autobahn-sync
Version: 0.2.1
Summary: Bring autobahn to your synchronous apps !
Home-page: https://github.com/Scille/autobahn_sync
Author: Emmanuel Leblond
Author-email: emmanuel.leblond@gmail.com
License: MIT
Keywords: autobahn autobahn.ws wamp twisted crochet flask
Platform: UNKNOWN
Classifier: Intended Audience :: Developers
Classifier: License :: OSI Approved :: MIT License
Classifier: Natural Language :: English
Classifier: Programming Language :: Python :: 2
Classifier: Programming Language :: Python :: 2.7
Classifier: Programming Language :: Python :: 3
Classifier: Programming Language :: Python :: 3.3
Classifier: Programming Language :: Python :: 3.4
